MANIFEST.in
README.rst
setup.py
githome/__init__.py
githome/cmd.py
githome/exc.py
githome/gh_client.c
githome/home.py
githome/model.py
githome/util.py
githome.egg-info/PKG-INFO
githome.egg-info/SOURCES.txt
githome.egg-info/dependency_links.txt
githome.egg-info/entry_points.txt
githome.egg-info/requires.txt
githome.egg-info/top_level.txt