Metadata-Version: 1.0
Name: githome
Version: 0.3.1
Summary: A tiny server for your git repositories, allowing configurable levels of access for multiple users.
Home-page: http://github.com/mbr/githome
Author: Marc Brinkmann
Author-email: git@marcbrinkmann.de
License: MIT
Platform: UNKNOWN
